rabbie/__init__.py
rabbie/broker_types/__init__.py
rabbie/broker_types/channel.py
rabbie/broker_types/relayed_types.py
rabbie/connection/__init__.py
rabbie/connection/details.py
rabbie/consumer/__init__.py
rabbie/consumer/consumer.py
rabbie/consumer/microconsumer.py
rabbie/consumer/listener/__init__.py
rabbie/consumer/listener/listener.py
rabbie/consumer/listener/listener_details.py
rabbie/consumer/listener/listener_status.py
rabbie/decoder/__init__.py
rabbie/decoder/decoder.py
rabbie/decoder/decoders/__init__.py
rabbie/decoder/decoders/auto_decoder.py
rabbie/decoder/decoders/json_decoder.py
rabbie/decoder/exceptions/__init__.py
rabbie/decoder/exceptions/decode_exception.py
rabbie/encoder/__init__.py
rabbie/encoder/encoder.py
rabbie/encoder/encoders/__init__.py
rabbie/encoder/encoders/auto_encoder.py
rabbie/encoder/encoders/json_encoder.py
rabbie/events/__init__.py
rabbie/events/event.py
rabbie/logger/__init__.py
rabbie/producer/__init__.py
rabbie/producer/producer.py
rabbie/producer/publisher/__init__.py
rabbie/producer/publisher/publisher.py
rabbie/supervisor/__init__.py
rabbie/supervisor/supervisor.py
rabbie-0.0.9.dist-info/LICENSE
rabbie-0.0.9.dist-info/METADATA
rabbie-0.0.9.dist-info/WHEEL
rabbie-0.0.9.dist-info/top_level.txt
rabbie-0.0.9.dist-info/RECORD
