Metadata-Version: 2.1
Name: rabbie
Version: 0.0.9
Summary: A simple, decorator interface for AMQP based message brokers
Home-page: https://github.com/scuffi/rabbie
Author: Archie Ferguson
Author-email: iamarchieferguson@gmail.com
License: MIT license
Classifier: Programming Language :: Python :: 3
Classifier: License :: OSI Approved :: MIT License
Classifier: Operating System :: OS Independent
License-File: LICENSE
Requires-Dist: pika
Requires-Dist: multiprocess
Requires-Dist: rich
Requires-Dist: watchdog
